deph/__init__.py
deph/analyzer.py
deph/helper.py
deph/isolator.py
deph/parser.py
deph/fmt/__init__.py
deph/fmt/bytes.py
deph/fmt/console.py
deph/fmt/datetime.py
deph/fmt/string.py
deph/types/__init__.py
deph/types/attrdefaultdict.py
deph/types/dataclasses.py
deph/utils/__init__.py
deph/utils/log.py
deph/utils/pip.py
deph/utils/zip.py
deph/visitors/__init__.py
deph/visitors/imported.py
deph/visitors/lowlevel.py
deph/visitors/usage.py
deph-1.0.0.dist-info/METADATA
deph-1.0.0.dist-info/WHEEL
deph-1.0.0.dist-info/licenses/LICENSE
deph-1.0.0.dist-info/RECORD
