Metadata-Version: 2.4
Name: deph
Version: 1.0.0
Summary: A developer utility to isolate, analyze, and compose Python code dependencies.
Project-URL: Homepage, https://github.com/dvm-shlee/deph
Author-email: SungHo Lee <shlee@unc.edu>
Maintainer-email: SungHo Lee <shlee@unc.edu>
License-Expression: MIT
License-File: LICENSE
Keywords: analysis,ast,dependency,import,isolation
Classifier: Development Status :: 5 - Production/Stable
Classifier: Framework :: Jupyter
Classifier: Intended Audience :: Developers
Classifier: License :: OSI Approved :: MIT License
Classifier: Programming Language :: Python :: 3
Classifier: Topic :: Software Development
Classifier: Topic :: Software Development :: Libraries :: Python Modules
Classifier: Topic :: Utilities
Requires-Python: >=3.9
Requires-Dist: requests
